xtrade_ai/__init__.cpython-313-x86_64-linux-gnu.so
xtrade_ai/__main__.cpython-313-x86_64-linux-gnu.so
xtrade_ai/_version.cpython-313-x86_64-linux-gnu.so
xtrade_ai/api.cpython-313-x86_64-linux-gnu.so
xtrade_ai/attention_mechanism.cpython-313-x86_64-linux-gnu.so
xtrade_ai/base_environment.cpython-313-x86_64-linux-gnu.so
xtrade_ai/cli.cpython-313-x86_64-linux-gnu.so
xtrade_ai/config.cpython-313-x86_64-linux-gnu.so
xtrade_ai/data_preprocessor.cpython-313-x86_64-linux-gnu.so
xtrade_ai/data_structures.cpython-313-x86_64-linux-gnu.so
xtrade_ai/policy_networks.cpython-313-x86_64-linux-gnu.so
xtrade_ai/xtrade_ai_framework.cpython-313-x86_64-linux-gnu.so
xtrade_ai/endpoints/__init__.cpython-313-x86_64-linux-gnu.so
xtrade_ai/endpoints/backtest.cpython-313-x86_64-linux-gnu.so
xtrade_ai/endpoints/fine_tuning.cpython-313-x86_64-linux-gnu.so
xtrade_ai/endpoints/health.cpython-313-x86_64-linux-gnu.so
xtrade_ai/endpoints/market_data.cpython-313-x86_64-linux-gnu.so
xtrade_ai/endpoints/models.cpython-313-x86_64-linux-gnu.so
xtrade_ai/endpoints/predictions.cpython-313-x86_64-linux-gnu.so
xtrade_ai/endpoints/training.cpython-313-x86_64-linux-gnu.so
xtrade_ai/modules/__init__.cpython-313-x86_64-linux-gnu.so
xtrade_ai/modules/action_selector.cpython-313-x86_64-linux-gnu.so
xtrade_ai/modules/backtest_engine.cpython-313-x86_64-linux-gnu.so
xtrade_ai/modules/baseline3_integration.cpython-313-x86_64-linux-gnu.so
xtrade_ai/modules/calibration.cpython-313-x86_64-linux-gnu.so
xtrade_ai/modules/callback_manager.cpython-313-x86_64-linux-gnu.so
xtrade_ai/modules/close_order_decision.cpython-313-x86_64-linux-gnu.so
xtrade_ai/modules/data_source_manager.cpython-313-x86_64-linux-gnu.so
xtrade_ai/modules/environment_setup.cpython-313-x86_64-linux-gnu.so
xtrade_ai/modules/integrated_analysis.cpython-313-x86_64-linux-gnu.so
xtrade_ai/modules/market_simulation.cpython-313-x86_64-linux-gnu.so
xtrade_ai/modules/meta_learning.cpython-313-x86_64-linux-gnu.so
xtrade_ai-1.2.0.dist-info/METADATA
xtrade_ai-1.2.0.dist-info/WHEEL
xtrade_ai-1.2.0.dist-info/entry_points.txt
xtrade_ai-1.2.0.dist-info/top_level.txt
xtrade_ai-1.2.0.dist-info/RECORD
xtrade_ai-1.2.0.dist-info/licenses/LICENSE
