Metadata-Version: 2.4
Name: xtrade-ai
Version: 1.2.0
Summary: A comprehensive reinforcement learning framework for algorithmic trading
Author-email: Anas Amu <anasamu7@gmail.com>
Maintainer-email: Anas Amu <anasamu7@gmail.com>
License: MIT
Project-URL: Homepage, https://github.com/anasamu/xtrade-ai-framework
Project-URL: Documentation, https://xtrade-ai-framework.readthedocs.io/en/latest/
Project-URL: Repository, https://github.com/anasamu/xtrade-ai-framework.git
Project-URL: Bug Tracker, https://github.com/anasamu/xtrade-ai-framework/issues
Project-URL: Source Code, https://github.com/anasamu/xtrade-ai-framework
Keywords: trading,reinforcement-learning,algorithmic-trading,machine-learning,finance,ai,trading-bot,quantitative-finance
Classifier: Development Status :: 4 - Beta
Classifier: Intended Audience :: Financial and Insurance Industry
Classifier: Intended Audience :: Developers
Classifier: License :: OSI Approved :: MIT License
Classifier: Operating System :: OS Independent
Classifier: Programming Language :: Python :: 3
Classifier: Programming Language :: Python :: 3.8
Classifier: Programming Language :: Python :: 3.9
Classifier: Programming Language :: Python :: 3.10
Classifier: Programming Language :: Python :: 3.11
Classifier: Programming Language :: Python :: 3.12
Classifier: Programming Language :: Python :: 3.13
Classifier: Topic :: Office/Business :: Financial :: Investment
Classifier: Topic :: Scientific/Engineering :: Artificial Intelligence
Classifier: Topic :: Software Development :: Libraries :: Python Modules
Requires-Python: <3.14,>=3.8
License-File: LICENSE
Requires-Dist: numpy<3.0.0,>=1.23.0
Requires-Dist: pandas<3.0.0,>=1.5.0
Requires-Dist: scikit-learn<2.0.0,>=1.3.0
Requires-Dist: torch>=2.0.0
Requires-Dist: stable-baselines3<3.0.0,>=2.0.0
Requires-Dist: gymnasium<1.1.0,>=0.29.1
Requires-Dist: shimmy<1.0.0,>=0.2.1
Requires-Dist: sb3-contrib<3.0.0,>=2.4.0
Requires-Dist: pandas-ta<1.0.0,>=0.3.14b0
Requires-Dist: xgboost<2.0.0,>=1.7.0
Requires-Dist: scipy<2.0.0,>=1.7.0
Requires-Dist: matplotlib<4.0.0,>=3.5.0
Requires-Dist: seaborn<1.0.0,>=0.11.0
Requires-Dist: cryptography<42.0.0,>=41.0.0
Requires-Dist: python-dotenv<1.0.0,>=0.19.0
Requires-Dist: pyyaml<7.0.0,>=6.0
Requires-Dist: click<9.0.0,>=8.0.0
Requires-Dist: requests<3.0.0,>=2.26.0
Requires-Dist: websocket-client<2.0.0,>=1.2.0
Requires-Dist: aiohttp<4.0.0,>=3.8.0
Requires-Dist: fastapi<1.0.0,>=0.100.0
Requires-Dist: uvicorn<1.0.0,>=0.20.0
Requires-Dist: bcrypt<5.0.0,>=4.0.0
Requires-Dist: psycopg2-binary<3.0.0,>=2.9.0
Requires-Dist: prometheus-client<1.0.0,>=0.12.0
Requires-Dist: psutil<6.0.0,>=5.8.0
Requires-Dist: pydantic<3.0.0,>=2.0.0
Requires-Dist: yfinance<0.2.60,>=0.2.18
Provides-Extra: development
Requires-Dist: setuptools>=65.0.0; extra == "development"
Requires-Dist: tomli_w<3.0.0,>=1.2.0; extra == "development"
Requires-Dist: wheel>=0.40.0; extra == "development"
Requires-Dist: cython>=3.0.0; extra == "development"
Requires-Dist: twine>=4.0.0; extra == "development"
Requires-Dist: pytest<8.0.0,>=7.0.0; extra == "development"
Requires-Dist: pytest-cov<4.0.0,>=3.0.0; extra == "development"
Requires-Dist: pytest-asyncio<1.0.0,>=0.18.0; extra == "development"
Requires-Dist: pytest-mock<4.0.0,>=3.6.0; extra == "development"
Requires-Dist: black<23.0.0,>=22.0.0; extra == "development"
Requires-Dist: flake8<5.0.0,>=4.0.0; extra == "development"
Requires-Dist: mypy<1.0.0,>=0.910; extra == "development"
Requires-Dist: jupyter<2.0.0,>=1.0.0; extra == "development"
Requires-Dist: ipykernel<7.0.0,>=6.0.0; extra == "development"
Requires-Dist: packaging<24.0,>=22.0; extra == "development"
Requires-Dist: pre-commit<3.0.0,>=2.15.0; extra == "development"
Requires-Dist: sphinx<5.0.0,>=4.0.0; extra == "development"
Requires-Dist: sphinx-rtd-theme<2.0.0,>=1.0.0; extra == "development"
Requires-Dist: myst-parser<1.0.0,>=0.15.0; extra == "development"
Provides-Extra: gpu
Requires-Dist: torch>=2.0.0; extra == "gpu"
Requires-Dist: tensorflow>=2.14.0; extra == "gpu"
Requires-Dist: cupy>=12.0.0; extra == "gpu"
Provides-Extra: cpu
Requires-Dist: torch>=2.0.0; extra == "cpu"
Requires-Dist: tensorflow-cpu>=2.14.0; extra == "cpu"
Requires-Dist: numpy>=1.21.0; extra == "cpu"
Dynamic: license-file
